requirements/__init__.py
requirements/__main__.py
requirements/_version.py
requirements/requirements.py
requirements.py-1.0.1.dist-info/LICENSE
requirements.py-1.0.1.dist-info/METADATA
requirements.py-1.0.1.dist-info/WHEEL
requirements.py-1.0.1.dist-info/entry_points.txt
requirements.py-1.0.1.dist-info/top_level.txt
requirements.py-1.0.1.dist-info/zip-safe
requirements.py-1.0.1.dist-info/RECORD
