Metadata-Version: 2.1
Name: requirements.py
Version: 1.0.1
Summary: Find updates for packages in requirements.txt on pypi
Author-email: cuzi <cuzi@openmail.cc>
License: GPL-3.0-or-later
Project-URL: Homepage, https://github.com/cvzi/requirements
Classifier: Programming Language :: Python
Classifier: Programming Language :: Python :: 3
Classifier: Programming Language :: Python :: 3.7
Classifier: Programming Language :: Python :: 3.8
Classifier: Programming Language :: Python :: 3.9
Classifier: Programming Language :: Python :: 3.10
Classifier: Programming Language :: Python :: 3.11
Classifier: License :: OSI Approved :: GNU General Public License v3 or later (GPLv3+)
Provides-Extra: testing
License-File: LICENSE
